[{"title":"2018 全国大学生软件测试大赛 安恒杯Web测试大赛 预选赛 部分题解","url":"/2018-AH-Autumn-Preliminary/"},{"title":"2018 安恒 7月月赛 部分题解","url":"/2018-AH-Jul/"},{"title":"2018 全国大学生软件测试大赛 安恒杯Web测试大赛 全国总决赛 部分题解","url":"/2018-AH-National-Final/"},{"title":"2018 安恒 11月月赛 部分题解","url":"/2018-AH-Nov/"},{"title":"2018 安恒 10月月赛 部分题解","url":"/2018-AH-Oct/"},{"title":"2018 全国大学生软件测试大赛 安恒杯Web测试大赛 省赛 部分题解","url":"/2018-AH-Provincial-Competition/"},{"title":"2018-AH-Sep","url":"/2018-AH-Sep/"},{"title":"2018 福建省高校网络空间安全大赛 百越杯 线上初赛 部分题解","url":"/2018-BYB-Preliminary/"},{"title":"2018 护网杯 线上预选赛 部分题解","url":"/2018-HWB-Preliminary/"},{"title":"2018 湖湘杯 线上初赛 部分题解","url":"/2018-HXB-Preliminary/"},{"title":"2018 Hacklu的一道代码审计","url":"/2018-Hacklu/"},{"title":"2018 MOCTF欢乐新春赛 部分题解","url":"/2018-MOCTF/"},{"title":"2019 安恒 1月月赛 部分题解","url":"/2019-AH-Jan/"},{"title":"2019 福建省高校网络空间安全大赛 百越杯 线上初赛 部分题解","url":"/2019-BYB-Preliminary/"},{"title":"2019 第十二届全国大学生信息安全竞赛 华北赛区 部分题解","url":"/2019-CISCN-Northern/"},{"title":"2019 第十二届全国大学生信息安全竞赛 创新实践能力赛 线上初赛 部分题解","url":"/2019-CISCN-Preliminary/"},{"title":"2019 D3CTF 部分题解","url":"/2019-D3CTF/"},{"title":"2019 De1CTF 部分题解","url":"/2019-De1CTF/"},{"title":"2019 高校网络信息安全管理运维挑战赛 部分题解","url":"/2019-EIS/"},{"title":"2019 广外网安大赛 部分题解","url":"/2019-GWCTF/"},{"title":"2019 黑盾杯 部分题解","url":"/2019-HDB/"},{"title":"2019 湖湘杯 线上初赛 部分题解","url":"/2019-HXB-Preliminary/"},{"title":"2019 安洵杯 部分题解","url":"/2019-I-SOON/"},{"title":"2019 强网杯 线上预选赛 部分题解","url":"/2019-QWB-Preliminary/"},{"title":"2019 SUCTF 部分题解","url":"/2019-SUCTF/"},{"title":"2019 西南石油大学 CTF 部分题解","url":"/2019-SWPUCTF/"},{"title":"2019 XCTF Final 部分题解","url":"/2019-XCTF-Final/"},{"title":"第四届XMan个人排位赛 部分题解","url":"/2019-XMan-Personal/"},{"title":"2019 XNUCA 线上预选赛 部分题解","url":"/2019-XNUCA-Preliminary/"},{"title":"2020 第十三届全国大学生信息安全竞赛 创新实践能力赛 线上初赛 部分题解","url":"/2020-CISCN/"},{"title":"2020 GACTF 部分题解","url":"/2020-GACTF/"},{"title":"2020 高校战“疫”网络安全分享赛 部分题解","url":"/2020-GXZY/"},{"title":"2020 网鼎杯 青龙之战 部分题解","url":"/2020-WDB-Azure-Dragon/"},{"title":"2020 网鼎杯 朱雀之战 部分题解","url":"/2020-WDB-Vermilion-Bird/"},{"title":"2020 网鼎杯 白虎之战 部分题解","url":"/2020-WDB-White-Tiger/"},{"title":"关于Dokcer的简单配置","url":"/Configure-Docker/"},{"title":"关于HEXO博客的配置","url":"/Configure-Hexo/"},{"title":"关于内网穿透的一些配置","url":"/Configure-Intranet-Penetration/"},{"title":"KALI安装后的一些准备","url":"/Configure-Kali/"},{"title":"关于MacBookPro的环境配置","url":"/Configure-MacBookPro/"},{"title":"关于服务器的一些配置","url":"/Configure-Server/"},{"title":"心之所向 素履以往","url":"/Daily-2018-Begin/"},{"title":"暂停一下","url":"/Daily-2020-Suspend/"},{"title":"关于某CTF交流群的入群题","url":"/Daily-CTF-Group-Question-4/"},{"title":"XCTF 攻防世界 题解","url":"/Platform-ADWorld/"},{"title":"关于BUUOJ的部分题解","url":"/Platform-BUUCTF/"},{"title":"关于新Bugku的题解","url":"/Platform-NewBugku/"},{"title":"关于在构建题目容器中学到的知识笔记","url":"/Study-CTFHUB-Bulid/"},{"title":"密码学 从入门到放弃","url":"/Study-Cryptology/"},{"title":"关于Electron的一些开发记录","url":"/Study-Electron/"},{"title":"Web安全执行函数修炼计划","url":"/Study-Execution-Function/"},{"title":"Web安全文件包含修炼计划","url":"/Study-File-Inclusion/"},{"title":"关于Flask与MongoDB的一些开发记录","url":"/Study-Flask-MongoDB/"},{"title":"LeetCode的数据结构与算法修炼计划","url":"/Study-LeetCode-Problemset/"},{"title":"初探MD5原理及哈希拓展攻击","url":"/Study-MD5/"},{"title":"关于Namp的学习","url":"/Study-Namp/"},{"title":"关于Nodejs的一些开发记录","url":"/Study-Nodejs/"},{"title":"浅析 Padding Oracle Attack","url":"/Study-Padding-Oracle/"},{"title":"关于AWD线下赛的一些整理","url":"/Study-Prepare-AWD/"},{"title":"关于RSA的学习","url":"/Study-RSA/"},{"title":"Web安全SQL修炼计划 基础挑战","url":"/Study-SQLI-Basic-Challenges/"},{"title":"一些关于SQL注入的绕过技巧","url":"/Study-SQLI-Tricks/"},{"title":"关于SSRF的初探","url":"/Study-SSRF/"},{"title":"关于反序列化漏洞的初探","url":"/Study-Unserialize/"},{"title":"Web安全文件上传修炼计划","url":"/Study-Upload-Labs/"},{"title":"Web安全XSS修炼计划","url":"/Study-XSS/"}]